LICENSE
MANIFEST.in
NOTICE
README.md
setup.cfg
setup.py
prometheus_speedtest/__init__.py
prometheus_speedtest/prometheus_speedtest.py
prometheus_speedtest/version.py
prometheus_speedtest.egg-info/PKG-INFO
prometheus_speedtest.egg-info/SOURCES.txt
prometheus_speedtest.egg-info/dependency_links.txt
prometheus_speedtest.egg-info/entry_points.txt
prometheus_speedtest.egg-info/requires.txt
prometheus_speedtest.egg-info/top_level.txt
prometheus_speedtest/__pycache__/__init__.cpython-312.pyc
prometheus_speedtest/__pycache__/version.cpython-312.pyc
prometheus_speedtest/static/index.html
tests/__init__.py
tests/prometheus_speedtest_test.py