Metadata-Version: 2.1
Name: prometheus_speedtest
Version: 0.9.16
Summary: Performs speedtest-cli tests and pushes metrics to Prometheus Pushgateway
Home-page: https://github.com/jeanralphaviles/prometheus_speedtest
Author: Jean-Ralph Aviles
Author-email: jeanralph.aviles+pypi@gmail.com
License: Apache License, Version 2.0
Keywords: prometheus,monitoring,speedtest,speedtest.net
Classifier: Development Status :: 5 - Production/Stable
Classifier: Environment :: Console
Classifier: Intended Audience :: Developers
Classifier: License :: OSI Approved :: Apache Software License
Classifier: Operating System :: OS Independent
Classifier: Topic :: System :: Monitoring
Classifier: Topic :: System :: Networking :: Monitoring
Classifier: Programming Language :: Python :: 3.13
Classifier: Programming Language :: Python
License-File: LICENSE
License-File: NOTICE
Requires-Dist: absl-py==2.1.0
Requires-Dist: prometheus_client==0.21.1
Requires-Dist: speedtest-cli==2.1.3
